CHANGELOG.md
LICENSE
MANIFEST.in
README.rst
setup.py
quantumpy/__init__.py
quantumpy/exceptions.py
quantumpy/quantum_api.py
quantumpy.egg-info/PKG-INFO
quantumpy.egg-info/SOURCES.txt
quantumpy.egg-info/dependency_links.txt
quantumpy.egg-info/requires.txt
quantumpy.egg-info/top_level.txt