Metadata-Version: 1.1
Name: quantumpy
Version: 0.1.9
Summary: An ultra simple wrapper for the Socialmetrix Quantum API, with basic functionality
Home-page: https://github.com/gdmachado/quantumpy
Author: Gustavo Machado
Author-email: gdmachado@me.com
License: UNKNOWN
Platform: UNKNOWN
Classifier: Development Status :: 2 - Pre-Alpha
Classifier: Intended Audience :: Developers
Classifier: Programming Language :: Python
Classifier: Natural Language :: English
Classifier: License :: OSI Approved :: Apache Software License
Classifier: Programming Language :: Python :: 2.6
Classifier: Programming Language :: Python :: 2.7
Classifier: Topic :: Software Development :: Libraries
Classifier: Operating System :: OS Independent
